autoxlsx/__init__.py
autoxlsx/cli.py
autoxlsx/models.py
autoxlsx/process.py
autoxlsx-0.2.0.dist-info/entry_points.txt
autoxlsx-0.2.0.dist-info/WHEEL
autoxlsx-0.2.0.dist-info/METADATA
autoxlsx-0.2.0.dist-info/RECORD
