Metadata-Version: 2.1
Name: autoxlsx
Version: 0.2.0
Summary: 
Author: KhalidCK
Author-email: khalidCK@win.local
Requires-Python: >=3.7,<4.0
Classifier: Programming Language :: Python :: 3
Classifier: Programming Language :: Python :: 3.7
Classifier: Programming Language :: Python :: 3.8
Requires-Dist: click (>=7.1.2,<8.0.0)
Requires-Dist: openpyxl (>=3.0.3,<4.0.0)
Requires-Dist: pyyaml (>=5.3.1,<6.0.0)
